{
  "_id": "680298593ccffd1c7912cbec",
  "ipo_id": "2018_ranjeet_mechatronics_limited_ipo",
  "__v": 0,
  "_metadata": {
    "sectionsAvailable": {
      "basicDetails": true,
      "tentativeSchedule": true,
      "lotSize": true,
      "timeline": false,
      "kpi": false,
      "financials": true,
      "promoterHolding": false,
      "objectives": false,
      "about": true,
      "subscriptionStatus": true,
      "contactDetails": true,
      "registrarDetails": true,
      "leadManagers": true,
      "listingDetails": true,
      "listingDayTrading": true,
      "faqs": true,
      "recommendationSummary": true,
      "prospectusLinks": true,
      "reservation": true,
      "anchorInvestors": false
    },
    "scrapedAt": "2025-04-18T18:12:51.122Z",
    "sourceUrl": "https://www.chittorgarh.com/ipo/ranjeet-mechatronics-ipo/923/"
  },
  "about": {
    "details": "<p>Incorporated in 1949, Ahmedabad based Ranjeet Mechatronics Limited is a company engaged in the business of providing specialized firefighting solutions as a system integrator. It provides end-to-end solutions in installation, designing, commission, testing, implementation, management and operational support for security and fire solutions. </p><p>Some of the projects completed by the company are-</p><p>1. Chennai Metro Rail Pump House<br>2. Goa Shipyard Modernisation Project Phase- 3A<br>3. Medical College Sola, Ahmedabad<br>4. Kalpana Chawla Government Medical, College, Karnal Haryana<br>5. Vardhaman Institute of Medical<br>Science (VIMS) Project</p><p>The company has 27 employees on its payroll.</p><p>Competitive Strengths-</p><p>1. Over 2 decades of experience<br>2. Perfectly positioned to benefit from government's focus on infrastructure<br>3. Good track record of timely completion of projects</p>"
  },
  "additionalTables": [
    {
      "heading": "Company Financials",
      "sanitizedHeading": "financials",
      "headers": [
        "Particulars",
        "For the year/period ended (in Rs. Lakhs)"
      ],
      "rows": [
        [
          null,
          "31-Mar-18",
          "31-Mar-17",
          "31-Mar-16",
          "31-Mar-15",
          "31-Mar-14"
        ],
        [
          "Total Assets",
          "2241.69",
          "2084.00",
          "1805.68",
          "1396.98",
          "764.98"
        ],
        [
          "Total Revenue",
          "1803.69",
          "1763.73",
          "2528.67",
          "2400.03",
          "1090.28"
        ],
        [
          "Profit After Tax",
          "91.31",
          "50.95",
          "16.08",
          "4.90",
          "3.09"
        ]
      ]
    }
  ],
  "basicDetails": {
    "ipoDate": "September 12, 2018 to September 17, 2018",
    "ipoListingDate": "Wed, Sep 26, 2018",
    "faceValue": "₹10 per share",
    "issuePrice": "₹25.00",
    "lotSize": "6,000 Shares",
    "issueSize": "18,00,000 shares (aggregating up to ₹4.50 Cr)",
    "issueType": "Fixed Price IPO",
    "listingAt": "BSE SME",
    "marketMakerPortion": "96,000 shares",
    "ipoOpenDate": "Wed, Sep 12, 2018",
    "ipoCloseDate": "Mon, Sep 17, 2018",
    "initiationOfRefunds": "Tue, Sep 25, 2018",
    "creditOfSharesToDemat": "Tue, Sep 25, 2018",
    "shareHoldingPreIssue": "47,99,980 shares",
    "shareHoldingPreIssueAll": [
      {
        "label": "Share Holding Pre Issue",
        "value": "47,99,980 shares"
      }
    ],
    "shareHoldingPostIssue": "65,99,980 shares",
    "shareHoldingPostIssueAll": [
      {
        "label": "Share Holding Post Issue",
        "value": "65,99,980 shares"
      }
    ]
  },
  "closing_date": "2018-09-16T18:30:00.000Z",
  "contactDetails": {
    "phone": "079 - 4000 9390",
    "email": "cs.compliance@ranjeet.co.in",
    "full_address": "Ranjeet Mechatronics Limited, Block A 407 - 4th Floor, Dev Aurum Anand Nagar Cross Road, Prahladnagar Road Ahmedabad - 380 015",
    "website": "http://www.ranjeet.co.in/"
  },
  "createdAt": "2025-04-18T18:22:17.558Z",
  "faqs": [
    {
      "question": "What is the Ranjeet Mechatronics IPO?",
      "answer": "<div itemprop=\"text\"><p>Ranjeet Mechatronics IPO<!-- --> is a <b>SME<!-- --> <!-- -->IPO<!-- --> of <!-- -->1800000<!-- --> equity shares</b> of the face value of ₹<!-- -->10<!-- --> aggregating up to ₹<!-- -->4.50<!-- --> Crores. The issue is priced at <span>₹25 per share</span>. The minimum order quantity is <!-- -->6000<!-- -->.</p><p>The <!-- -->IPO<!-- --> <b>opens on <!-- -->September 12, 2018</b>, and <b>closes on <!-- -->September 17, 2018</b>.</p><p>Alankit Assignments Ltd<!-- --> is the registrar for the <!-- -->IPO<!-- -->. The shares are proposed to be listed on <!-- -->BSE SME<!-- -->.</p></div>"
    },
    {
      "question": "How to apply in Ranjeet Mechatronics IPO through Zerodha?",
      "answer": "<div itemprop=\"text\"><p>Zerodha customers can apply online in <!-- -->Ranjeet Mechatronics IPO<!-- --> using UPI as a payment gateway. Zerodha customers can apply in <!-- -->Ranjeet Mechatronics IPO<!-- --> by login into Zerodha Console (back office) and submitting an IPO application form.</p><p><strong>Steps to apply in <!-- -->Ranjeet Mechatronics IPO<!-- --> through Zerodha</strong></p><ol><li>Visit the Zerodha website and login to Console.</li><li>Go to Portfolio and click the IPOs link.</li><li>Go to the '<!-- -->Ranjeet Mechatronics IPO<!-- -->' row and click the 'Bid' button.</li><li>Enter your UPI ID, Quantity, and Price.</li><li>Submit IPO application form.</li><li>Visit the UPI App (net banking or BHIM) to approve the mandate.</li></ol><p>Visit <a href=\"/broker/zerodha/ipo/18/\" title=\"Zerodha IPO Application Process Review\">Zerodha IPO Application Process Review</a> for more detail.</p></div>"
    },
    {
      "question": "When Ranjeet Mechatronics IPO will open?",
      "answer": "<div itemprop=\"text\"><p>The Ranjeet Mechatronics IPO opens on September 12, 2018 and closes on September 17, 2018.</p></div>"
    },
    {
      "question": "What is the lot size of Ranjeet Mechatronics IPO?",
      "answer": "<div itemprop=\"text\"><p>Ranjeet Mechatronics IPO<!-- --> <b>lot size is <!-- -->6000</b>, and the <b>minimum amount required is <span>₹1,50,000</span></b>.</p></div>"
    },
    {
      "question": "How to apply for Ranjeet Mechatronics IPO?",
      "answer": "<div itemprop=\"text\"><p>You can apply in <!-- -->Ranjeet Mechatronics IPO<!-- --> online using either <a href=\"/article/upi-payment-option-ipo-application-explained/382/\">UPI</a> or ASBA as a payment method. ASBA IPO application is available in the net banking of your bank account. UPI IPO application is offered by brokers who don't offer banking services. Read more detail about applying IPO online through <a href=\"/broker/zerodha/ipo/18/\" title=\"Zerodha IPO Review\"><b>Zerodha</b></a>, <a href=\"/broker/upstox/ipo/33/\" title=\"Upstox IPO Review\">Upstox</a>, <a href=\"/broker/5paisa/ipo/4/\" title=\"5Paisa IPO Review\">5Paisa</a>, <a href=\"/broker/edelweiss_broking/ipo/34/\" title=\"Nuvama IPO Review\">Nuvama</a>, <a href=\"/broker/hdfc-securities/ipo/6/\" title=\"HDFC Bank IPO Review\">HDFC Bank</a>, and <a href=\"/broker/sbi-capital/ipo/19/\" title=\"SBI Capital IPO Review\">SBI Bank</a>.</p></div>"
    },
    {
      "question": "When is Ranjeet Mechatronics IPO allotment?",
      "answer": "<div itemprop=\"text\"><p>The finalization of Basis of Allotment for <!-- -->Ranjeet Mechatronics IPO<!-- --> will be done on <!-- -->Friday, September 21, 2018<!-- -->, and the allotted shares will be credited to your demat account by <!-- -->Tuesday, September 25, 2018<!-- -->. Check the <a href=\"/ipo_allotment_status/ranjeet-mechatronics-ipo/923/\" title=\"Ranjeet Mechatronics IPO Allotment Status\">Ranjeet Mechatronics IPO<!-- --> allotment status</a>.</p></div>"
    },
    {
      "question": "When is Ranjeet Mechatronics IPO listing date?",
      "answer": "<div itemprop=\"text\"><p>The <!-- -->Ranjeet Mechatronics IPO<!-- --> listing date is on <b>Wednesday, September 26, 2018</b>.</p></div>"
    }
  ],
  "ipoName": "Ranjeet Mechatronics",
  "issue_price": "₹25.00",
  "issue_price_numeric": 25,
  "issue_size": "18,00,000 shares (aggregating up to ₹4.50 Cr)",
  "issue_size_numeric": 18,
  "leadManagerReports": [
    {
      "text": "IPO Lead Manager Performance Summary",
      "url": "/report/ipo_lead_manager_performance_tracker/19/"
    },
    {
      "text": "IPO Lead Manager Performance Tracker",
      "url": "/report/ipo-lead-manager-vs-listing-gain/99/17/"
    }
  ],
  "leadManagers": [
    {
      "name": "Beeline Broking Ltd",
      "url": "/report/ipo-lead-manager-review/112/160/",
      "performance_link": "/report/ipo-lead-manager-vs-listing-gain/99/160/"
    }
  ],
  "listingDayTrading": {
    "data": {
      "final_issue_price": {
        "bse_sme": "25.00"
      },
      "open": {
        "bse_sme": "27.50"
      },
      "low": {
        "bse_sme": "27.50"
      },
      "high": {
        "bse_sme": "28.85"
      },
      "last_trade": {
        "bse_sme": "28.85"
      }
    },
    "performance_link": {
      "text": "Check IPO Performance…",
      "url": "/ipo/ipo_perf_tracker.asp"
    }
  },
  "listingDetails": {
    "pre_open_links": [
      {
        "text": "Pre-Open Session - BSE",
        "url": "https://www.bseindia.com/eqstreamer/StockTickerSplPreOpen.html"
      }
    ],
    "ipo_date": "September 26 2018",
    "bse_script_code": "541945",
    "isin": "INE01A501019",
    "final_issue_price": "25 per share"
  },
  "listing_date": "2018-09-25T18:30:00.000Z",
  "listing_gains": "15.40%",
  "listing_gains_numeric": 15.4,
  "logo": "https://www.chittorgarh.net/images/ipo/ranjeet-logo.jpg",
  "logo_url": "https://www.chittorgarh.net/images/ipo/ranjeet-logo.jpg",
  "lotSize": {
    "summary": "Investors can bid for a minimum of 6000 shares and in multiples thereof. The following table depicts the minimum and maximum investment by Retail Investors and HNI in terms of shares and amount.",
    "applications": {
      "retail_min": {
        "application": "Retail (Min)",
        "lots": "1",
        "shares": "6000",
        "amount": "150000"
      },
      "retail_max": {
        "application": "Retail (Max)",
        "lots": "1",
        "shares": "6000",
        "amount": "150000"
      },
      "hni_min": {
        "application": "HNI (Min)",
        "lots": "2",
        "shares": "12000",
        "amount": "300000"
      },
      "lot_size": {
        "application": "Lot Size Calculator"
      }
    },
    "calculator_link": {
      "text": "Lot Size Calculator",
      "url": "/ipo-hni-funding-cost-calculator/ranjeet-mechatronics-ipo/923/"
    }
  },
  "lot_size": 6,
  "opening_date": "2018-09-11T18:30:00.000Z",
  "pageHeading": "Ranjeet Mechatronics Limited IPO (Ranjeet Mechatronics IPO) Detail",
  "pageTitle": "Ranjeet Mechatronics IPO Date, Price, GMP, Review, Details",
  "prospectusLinks": [
    {
      "text": "Ranjeet Mechatronics IPO DRHP",
      "url": "https://www.bseindia.com/downloads/ipo/20188112449Final%20DRHP_01082018.pdf"
    },
    {
      "text": "Ranjeet Mechatronics IPO RHP",
      "url": "https://www.sebi.gov.in/filings/public-issues/oct-2018/ranjeet-mechatronics-limited_40577.html"
    }
  ],
  "recommendationSummary": {
    "recommendations": {
      "brokersbrokers": {
        "subscribe": "1",
        "neutral": "0",
        "avoid": "0"
      },
      "membersmembers": {
        "subscribe": "0",
        "neutral": "0",
        "avoid": "0"
      }
    },
    "links": [
      {
        "text": "Read All Reviews",
        "url": "/ipo-recommendation/ranjeet-mechatronics-ipo/923/"
      },
      {
        "text": "Post Your Review",
        "url": "#"
      },
      {
        "text": "Manage Reviews",
        "url": "#"
      }
    ]
  },
  "registrarDetails": {
    "name": "Alankit Assignments Ltd",
    "phone": "(011) 4254 1234",
    "email": "ipo@alankit.com",
    "website": "http://ipo.alankit.com/"
  },
  "reservation": {
    "summary": "Ranjeet Mechatronics IPO offers 1800000 shares. 852000 (47.33%) to NII 852000 (47.33%) to RII.",
    "allocation": [
      {
        "investor_category": "Anchor Investor Shares Offered",
        "shares_offered": "-"
      },
      {
        "investor_category": "Market Maker Shares Offered",
        "shares_offered": "96000 (5.33%)"
      },
      {
        "investor_category": "Other Shares Offered",
        "shares_offered": "852000 (47.33%)"
      },
      {
        "investor_category": "Retail Shares Offered",
        "shares_offered": "852000 (47.33%)"
      },
      {
        "investor_category": "Total Shares Offered",
        "shares_offered": "1800000 (100%)"
      }
    ]
  },
  "scraped_at": "2025-04-18T18:22:17.557Z",
  "source_url": "",
  "status": "listed",
  "subscriptionStatus": {
    "summary": "The Ranjeet Mechatronics IPO is subscribed 69.75 times on September 17 2018 6:29:02 PM (Day 3). The public issue subscribed 62.03 times in the retail category [.] times in the QIB category and 77.48 times in the NII category. Check Day by Day Subscription Details (Live Status)",
    "overall": {
      "nii": {
        "category": "NII",
        "subscription_times": "77.48",
        "shares_offered": "852000",
        "shares_bid_for": "66012000"
      },
      "retail": {
        "category": "Retail",
        "subscription_times": "62.03",
        "shares_offered": "852000",
        "shares_bid_for": "52848000"
      },
      "total": {
        "category": "Total",
        "subscription_times": "69.75",
        "shares_offered": "1704000",
        "shares_bid_for": "118860000"
      }
    }
  },
  "tentativeDetails": {
    "ipo_date": "5 PM on September 17 2018",
    "tentative_allotment": "Fri Sep 21 2018",
    "initiation_of_refunds": "Tue Sep 25 2018",
    "credit_of_shares_to_demat": "Tue Sep 25 2018"
  },
  "updatedAt": "2025-04-19T04:39:20.028Z",
  "updated_at": "2025-04-18T18:22:17.557Z",
  "year": 2018,
  "worst_listing_gains": "15.40%",
  "worst_listing_gains_numeric": 15.4
}